syng/.mypy_cache/.gitignore
syng/.mypy_cache/3.14/@plugins_snapshot.json
syng/.mypy_cache/3.14/Crypto/Cipher/AES.data.json
syng/.mypy_cache/3.14/Crypto/Cipher/AES.meta.json
syng/.mypy_cache/3.14/Crypto/Cipher/ChaCha20_Poly1305.data.json
syng/.mypy_cache/3.14/Crypto/Cipher/ChaCha20_Poly1305.meta.json
syng/.mypy_cache/3.14/Crypto/Cipher/__init__.data.json
syng/.mypy_cache/3.14/Crypto/Cipher/__init__.meta.json
syng/.mypy_cache/3.14/Crypto/Cipher/_mode_cbc.data.json
syng/.mypy_cache/3.14/Crypto/Cipher/_mode_cbc.meta.json
syng/.mypy_cache/3.14/Crypto/Cipher/_mode_ccm.data.json
syng/.mypy_cache/3.14/Crypto/Cipher/_mode_ccm.meta.json
syng/.mypy_cache/3.14/Crypto/Cipher/_mode_cfb.data.json
syng/.mypy_cache/3.14/Crypto/Cipher/_mode_cfb.meta.json
syng/.mypy_cache/3.14/Crypto/Cipher/_mode_ctr.data.json
syng/.mypy_cache/3.14/Crypto/Cipher/_mode_ctr.meta.json
syng/.mypy_cache/3.14/Crypto/Cipher/_mode_eax.data.json
syng/.mypy_cache/3.14/Crypto/Cipher/_mode_eax.meta.json
syng/.mypy_cache/3.14/Crypto/Cipher/_mode_ecb.data.json
syng/.mypy_cache/3.14/Crypto/Cipher/_mode_ecb.meta.json
syng/.mypy_cache/3.14/Crypto/Cipher/_mode_gcm.data.json
syng/.mypy_cache/3.14/Crypto/Cipher/_mode_gcm.meta.json
syng/.mypy_cache/3.14/Crypto/Cipher/_mode_ocb.data.json
syng/.mypy_cache/3.14/Crypto/Cipher/_mode_ocb.meta.json
syng/.mypy_cache/3.14/Crypto/Cipher/_mode_ofb.data.json
syng/.mypy_cache/3.14/Crypto/Cipher/_mode_ofb.meta.json
syng/.mypy_cache/3.14/Crypto/Cipher/_mode_openpgp.data.json
syng/.mypy_cache/3.14/Crypto/Cipher/_mode_openpgp.meta.json
syng/.mypy_cache/3.14/Crypto/Cipher/_mode_siv.data.json
syng/.mypy_cache/3.14/Crypto/Cipher/_mode_siv.meta.json
syng/.mypy_cache/3.14/Crypto/Util/__init__.data.json
syng/.mypy_cache/3.14/Crypto/Util/__init__.meta.json
syng/.mypy_cache/3.14/Crypto/Util/_raw_api.data.json
syng/.mypy_cache/3.14/Crypto/Util/_raw_api.meta.json
syng/.mypy_cache/3.14/Crypto/__init__.data.json
syng/.mypy_cache/3.14/Crypto/__init__.meta.json
syng-2.3.0.dist-info/WHEEL
syng-2.3.0.dist-info/entry_points.txt
syng-2.3.0.dist-info/METADATA
syng-2.3.0.dist-info/RECORD
