Metadata-Version: 2.4
Name: syng
Version: 2.3.0
Summary: Easily host karaoke events
Keywords: karaoke,youtube,web,audio,video,player,qt
Author: Christoph Stahl
Author-email: Christoph Stahl <christoph.stahl@tu-dortmund.de>
License-Expression: AGPL-3.0-or-later
Classifier: Development Status :: 5 - Production/Stable
Classifier: Environment :: Web Environment
Classifier: Environment :: X11 Applications :: Qt
Classifier: Framework :: AsyncIO
Classifier: Intended Audience :: End Users/Desktop
Classifier: License :: OSI Approved :: GNU Affero General Public License v3 or later (AGPLv3+)
Classifier: Operating System :: POSIX :: Linux
Classifier: Programming Language :: Python :: 3.12
Classifier: Topic :: Multimedia :: Sound/Audio :: Players
Classifier: Topic :: Multimedia :: Video :: Display
Classifier: Typing :: Typed
Requires-Dist: python-socketio>=5.14.3
Requires-Dist: aiohttp>=3.9.1
Requires-Dist: platformdirs>=4.0.0
Requires-Dist: yt-dlp[default]>=2025.12.8
Requires-Dist: qrcode>=8.2
Requires-Dist: packaging>=25.0
Requires-Dist: minio>=7.2.0 ; extra == 'client'
Requires-Dist: pillow>=11.0.0 ; extra == 'client'
Requires-Dist: qrcode>=8.2 ; extra == 'client'
Requires-Dist: pymediainfo>=6.1.0 ; extra == 'client'
Requires-Dist: pyyaml>=6.0.1 ; extra == 'client'
Requires-Dist: pyqt6>=6.7.1 ; extra == 'client'
Requires-Dist: mpv>=1.0.7 ; extra == 'client'
Requires-Dist: qasync>=0.27.1 ; extra == 'client'
Requires-Dist: alt-profanity-check>=1.4.1 ; extra == 'profanity'
Requires-Python: >=3.12, <4.0
Project-URL: Bug Tracker, https://github.com/christofsteel/syng/issues
Project-URL: homepage, https://syng.rocks
Project-URL: repository, https://git.k-fortytwo.de/christofsteel/syng
Provides-Extra: client
Provides-Extra: profanity
